avenger-0.0.8.dist-info/METADATA
avenger-0.0.8.dist-info/WHEEL
avenger-0.0.8.dist-info/entry_points.txt
avenger-0.0.8.dist-info/license_files/LICENSE
avenger/__init__.py
avenger/altair_utils.py
avenger/_avenger.abi3.so
avenger-0.0.8.dist-info/RECORD
