Metadata-Version: 2.3
Name: avenger
Version: 0.0.8
License-File: LICENSE
Summary: A Visualization Engine and Renderer
License: BSD-3-Clause
